pathmind/__init__.py
pathmind/policy.py
pathmind/simulation.py
pathmind-0.4.dist-info/METADATA
pathmind-0.4.dist-info/WHEEL
pathmind-0.4.dist-info/top_level.txt
pathmind-0.4.dist-info/RECORD
