Metadata-Version: 2.1
Name: pathmind
Version: 0.4
Summary: Python Simulations 
Home-page: https://github.com/PathmindAI/pathmind_api
Author: Max Pumperla
Author-email: max@pathmind.com
License: MIT
Download-URL: https://github.com/PathmindAPI/pathmind_api/tarball/0.4
Platform: UNKNOWN
Classifier: Development Status :: 3 - Alpha
Classifier: Intended Audience :: Developers
Classifier: Environment :: Console
Classifier: License :: OSI Approved :: Apache Software License
Classifier: Operating System :: OS Independent
Classifier: Programming Language :: Python :: 3
Requires-Dist: pyyaml
Requires-Dist: tensorflow
Requires-Dist: requests
Requires-Dist: prettytable
Requires-Dist: gym
Requires-Dist: or-gym
Provides-Extra: tests
Requires-Dist: pytest ; extra == 'tests'
Requires-Dist: flake8 ; extra == 'tests'
Requires-Dist: flake8-debugger ; extra == 'tests'
Requires-Dist: pre-commit ; extra == 'tests'
Requires-Dist: pandas ; extra == 'tests'
